[
  {
    "ContainingType": "Backend.Routes.AuthEndpoints\u002B\u003C\u003Ec",
    "Method": "\u003CMapAuthEndpoints\u003Eb__0_1",
    "RelativePath": "api/users/login",
    "HttpMethod": "POST",
    "IsController": false,
    "Order": 0,
    "Parameters": [],
    "ReturnTypes": [
      {
        "Type": "System.Void",
        "MediaTypes": [],
        "StatusCode": 200
      }
    ]
  },
  {
    "ContainingType": "Backend.Routes.AuthEndpoints\u002B\u003C\u003Ec",
    "Method": "\u003CMapAuthEndpoints\u003Eb__0_0",
    "RelativePath": "api/users/register",
    "HttpMethod": "POST",
    "IsController": false,
    "Order": 0,
    "Parameters": [
      {
        "Name": "request",
        "Type": "Backend.Models.Dto.AuthRequestDto",
        "IsRequired": true
      }
    ],
    "ReturnTypes": [
      {
        "Type": "System.Void",
        "MediaTypes": [],
        "StatusCode": 200
      }
    ]
  }
]